LICENSE
README.rst
setup.py
bankbarcode/__init__.py
bankbarcode/bankbarcode.py
bankbarcode/cuaderno57.py
bankbarcode.egg-info/PKG-INFO
bankbarcode.egg-info/SOURCES.txt
bankbarcode.egg-info/dependency_links.txt
bankbarcode.egg-info/requires.txt
bankbarcode.egg-info/top_level.txt