Metadata-Version: 2.1
Name: bankbarcode
Version: 0.3.0
Summary: barcodes for financial documents
Home-page: https://github.com/gisce/bankbarcode
Author: GISCE-TI, S.L.
Author-email: devel@gisce.net
License: GNU Affero General Public License v3
License-File: LICENSE
